uspy/__init__.py
uspy/dataobject.py
uspy/plotting.py
uspy/roi.py
uspy/utility.py
uspy/version.py
uspy/leem/__init__.py
uspy/leem/base.py
uspy/leem/base_old.py
uspy/leem/cluster.py
uspy/leem/driftnorm.py
uspy/leem/plotting.py
uspy/leem/processing.py
uspy/leem/rsm.py
uspy/leem/utility.py
uspy/stm/__init__.py
uspy/stm/base.py
uspy/stm/plotting.py
uspy/stm/processing.py
uspy/xps/__init__.py
uspy/xps/io.py
uspy/xps/models.py
uspy/xps/plotting.py
uspy/xps/processing.py
uspy/xps/rsf.db
uspy/xps/spectrum.py
uspy-0.10.1.dist-info/LICENSE.md
uspy-0.10.1.dist-info/METADATA
uspy-0.10.1.dist-info/WHEEL
uspy-0.10.1.dist-info/top_level.txt
uspy-0.10.1.dist-info/RECORD
